{
  "basics": {
    "name": "Aaron Nonaka",
    "label": "Student",
    "picture": "https://nonakaa.github.io/images/profesionalPicTest.jpg",
    "email": "nonakaa@hawaii.edu",
    "phone": "808-258-6008",
    "website": "https://nonakaa.github.io",
    "summary": "I am studying for a B.S. in Computer Science in the Department of Information and Computer Sciences at the University of Hawaii. I expect to graduate in Spring, 2020.",
    "location": {
      "address": "99-716 Puluniu Loop",
      "postalCode": "96701",
      "city": "Aiea",
      "countryCode": "USA",
      "region": "Hawaii"
    },
    "profiles": [
      {
        "network": "github",
        "username": "nonakaa",
        "url": "http://github.com/nonakaa"
      },
      {
        "network": "linkedin",
        "username": "aaronnonaka",
        "url": "https://www.linkedin.com/in/aaron-nonaka-aa1751146/"
      }
    ]
  },
  "interests": [
    {
      "name": "programing",
      "keywords": [
      ]
    }
  ],
  "skills": [
    {
      "name": "Languages and Frameworks",
      "level": "",
      "keywords": [
        
        "Java",
        "Javascript",
        
      ]
    },
    
  ],
  "education": [
    {
      "institution": "University of Hawaii, Honolulu, HI",
      "area": "Computer Science (expected Spring, 2020)",
      "studyType": "B.S.",
      "startDate": "2016-09-01",
      "endDate": "Present",
      "gpa": "3.0",
      "courses": [
      ]
    }
  ],
  "work": [
    {
      "company": "Manoa Valley Church After School Care",
      "position": "Leader",
      "website": "",
      "startDate": "2016-05-01",
      "endDate": "Present",
      "summary": "After school leader",
      "highlights": [
        "Supervise children","Plan activities"
      ]
    },
    {
      "company": "Running Room",
      "position": "Sales Associate",
      "website": "",
      "startDate": "2017-04-01",
      "endDate": "present",
      "summary": "",
      "highlights": [
        "Assist customers"
      ]
    }
  ],
  "volunteer": [
    
      
  ],
  "awards": [
    
  ],
  "references": [
    {
      "name": "Available upon request",
      "reference": ""
    }
  ]
}
